booktool/__init__.py
booktool/__main__.py
booktool/isbnsearch.py
booktool/util.py
booktool/worldcat.py
booktool/audio/__init__.py
booktool/audio/group.py
booktool/audio/track.py
booktool/visual/__init__.py
booktool/visual/epub.py
booktool/visual/tools.py
booktool-0.7.0.dist-info/METADATA
booktool-0.7.0.dist-info/WHEEL
booktool-0.7.0.dist-info/entry_points.txt
booktool-0.7.0.dist-info/top_level.txt
booktool-0.7.0.dist-info/RECORD
