Metadata-Version: 2.1
Name: booktool
Version: 0.7.0
Summary: eBook (EPUB and Audiobook) management tool
Home-page: https://github.com/chbrown/booktool
Author: Christopher Brown
Author-email: io@henrian.com
License: MIT
Platform: UNKNOWN
Classifier: Development Status :: 3 - Alpha
Classifier: Environment :: Console
Classifier: Intended Audience :: Developers
Classifier: Intended Audience :: Education
Classifier: Intended Audience :: Science/Research
Classifier: License :: OSI Approved :: MIT License
Classifier: Programming Language :: Python
Classifier: Topic :: Education
Classifier: Topic :: Multimedia :: Sound/Audio
Classifier: Topic :: Multimedia :: Sound/Audio :: Speech
Classifier: Topic :: Scientific/Engineering
Classifier: Topic :: System :: Archiving
Classifier: Topic :: System :: Archiving :: Backup
Classifier: Topic :: Text Processing :: General
Requires-Python: >=3.6
Requires-Dist: click (>=7.0)
Requires-Dist: filesystemlib
Requires-Dist: mutagen (>=1.42)
